mhtg/client.py
mhtg/context.py
mhtg/model.py
mhtg-0.0.3.dist-info/LICENSE
mhtg-0.0.3.dist-info/METADATA
mhtg-0.0.3.dist-info/WHEEL
mhtg-0.0.3.dist-info/top_level.txt
mhtg-0.0.3.dist-info/RECORD
