Metadata-Version: 2.1
Name: mhtg
Version: 0.0.3
Summary: mhtg
Home-page: UNKNOWN
Maintainer: Zachary Buhman
Maintainer-email: zack@buhman.org
License: UNKNOWN
Keywords: async,http,h11,trio
Platform: UNKNOWN
Classifier: Development Status :: 2 - Pre-Alpha
Classifier: Intended Audience :: Developers
Classifier: License :: OSI Approved :: GNU General Public License v3 or later (GPLv3+)
Classifier: Operating System :: POSIX :: Linux
Classifier: Programming Language :: Python
Classifier: Programming Language :: Python :: 3 :: Only
Classifier: Programming Language :: Python :: 3.7
Requires-Dist: h11 (==0.8.1)
Requires-Dist: trio (==0.11.0)
